.readthedocs.yml
CHANGES.rst
LICENSE.txt
MANIFEST.in
README.md
pyproject.toml
setup.cfg
setup.py
as3lib_miniAMF.egg-info/PKG-INFO
as3lib_miniAMF.egg-info/SOURCES.txt
as3lib_miniAMF.egg-info/dependency_links.txt
as3lib_miniAMF.egg-info/requires.txt
as3lib_miniAMF.egg-info/top_level.txt
doc/bugs.rst
doc/conf.py
doc/download.rst
doc/install.rst
doc/license.rst
doc/maintainers.rst
doc/_static/favicon.ico
doc/architecture/adapters.rst
doc/architecture/classmapping.rst
doc/architecture/future.rst
doc/architecture/index.rst
doc/architecture/overview.rst
doc/architecture/typemap.rst
doc/architecture/examples/adapters/myadapter.py
doc/architecture/examples/adapters/mymodule.py
doc/architecture/examples/class-mapping/alias-decorator.py
doc/architecture/examples/class-mapping/example-classes.as
doc/architecture/examples/class-mapping/example-classes.py
miniamf/__init__.py
miniamf/_version.py
miniamf/alias.py
miniamf/amf0.py
miniamf/amf3.py
miniamf/codec.py
miniamf/sol.py
miniamf/versions.py
miniamf/xml.py
miniamf/_accel/__init__.py
miniamf/_accel/amf0.pxd
miniamf/_accel/amf0.pyx
miniamf/_accel/amf3.pxd
miniamf/_accel/amf3.pyx
miniamf/_accel/codec.pxd
miniamf/_accel/codec.pyx
miniamf/_accel/util.pxd
miniamf/_accel/util.pyx
miniamf/adapters/__init__.py
miniamf/adapters/_array.py
miniamf/adapters/_collections.py
miniamf/adapters/_decimal.py
miniamf/adapters/_django_contrib_auth_models.py
miniamf/adapters/_django_db_models_base.py
miniamf/adapters/_django_db_models_fields.py
miniamf/adapters/_django_db_models_query.py
miniamf/adapters/_django_utils_translation.py
miniamf/adapters/_sets.py
miniamf/adapters/_sqlalchemy_orm.py
miniamf/adapters/_sqlalchemy_orm_collections.py
miniamf/adapters/_weakref.py
miniamf/adapters/util.py
miniamf/flex/__init__.py
miniamf/flex/data.py
miniamf/flex/messaging.py
miniamf/remoting/__init__.py
miniamf/remoting/amf0.py
miniamf/remoting/amf3.py
miniamf/remoting/client/__init__.py
miniamf/remoting/gateway/__init__.py
miniamf/remoting/gateway/django.py
miniamf/remoting/gateway/wsgi.py
miniamf/tests/__init__.py
miniamf/tests/test_adapters.py
miniamf/tests/test_adapters_util.py
miniamf/tests/test_alias.py
miniamf/tests/test_amf0.py
