Metadata-Version: 2.4
Name: as3lib-miniAMF
Version: 3
Summary: A fork of Mini-AMF using up to date dependencies.
Author-email: ajdelguidice <ajdelguidice@gmail.com>
License-Expression: MIT
Project-URL: Homepage, https://github.com/ajdelguidice/as3lib-miniAMF
Keywords: amf,amf0,amf3,actionscript,air,flash,flashplayer,bytearray,recordset,decoder,encoder,sharedobject,lso,sol
Classifier: Operating System :: OS Independent
Classifier: Programming Language :: Python :: 3.10
Classifier: Topic :: Utilities
Requires-Python: >=3.10
License-File: LICENSE.txt
Requires-Dist: defusedxml
Dynamic: license-file
